{"Sammy":{"66":{"id":66,"name":"Batgirl V","Gender":"Female","Eye color":"-","Race":"-","Hair color":"-","Height":-99,"Publisher":"DC Comics","Skin color":"-","Alignment":"good","Weight":-99,"Power":"-"},"69":{"id":69,"name":"Batman","Gender":"Male","Eye color":"blue","Race":"Human","Hair color":"Black","Height":178,"Publisher":"DC Comics","Skin color":"-","Alignment":"good","Weight":77,"Power":["Agility","Durability","Stealth","Underwater breathing","Marksmanship","Weapons Master","Intelligence","Super Strength","Stamina","Super Speed","Weapon-based Powers","Peak Human Condition","Reflexes","Gliding","Power Suit","Vision - Night","Vision - Infrared"]},"77":{"id":77,"name":"Ben 10","Gender":"Male","Eye color":"-","Race":"-","Hair color":"-","Height":-99,"Publisher":"DC Comics","Skin color":"-","Alignment":"good","Weight":-99,"Power":["Omnitrix","Shapeshifting"]},"88":{"id":88,"name":"Bird-Man","Gender":"Male","Eye color":"-","Race":"Human","Hair color":"-","Height":-99,"Publisher":"Marvel Comics","Skin color":"-","Alignment":"bad","Weight":-99,"Power":["Flight","Super Strength","Animal Oriented Powers","Natural Weapons"]}}}